odoo/addons/sale_multicompany_reporting_currency/README.rst
odoo/addons/sale_multicompany_reporting_currency/__init__.py
odoo/addons/sale_multicompany_reporting_currency/__manifest__.py
odoo/addons/sale_multicompany_reporting_currency/i18n/es.po
odoo/addons/sale_multicompany_reporting_currency/i18n/sale_multicompany_reporting_currency.pot
odoo/addons/sale_multicompany_reporting_currency/models/__init__.py
odoo/addons/sale_multicompany_reporting_currency/models/res_company.py
odoo/addons/sale_multicompany_reporting_currency/models/res_config_settings.py
odoo/addons/sale_multicompany_reporting_currency/models/sale_order.py
odoo/addons/sale_multicompany_reporting_currency/readme/CONTRIBUTORS.rst
odoo/addons/sale_multicompany_reporting_currency/readme/DESCRIPTION.rst
odoo/addons/sale_multicompany_reporting_currency/static/description/icon.png
odoo/addons/sale_multicompany_reporting_currency/static/description/index.html
odoo/addons/sale_multicompany_reporting_currency/tests/__init__.py
odoo/addons/sale_multicompany_reporting_currency/tests/test_amount_multicompany_reporting_currency.py
odoo/addons/sale_multicompany_reporting_currency/views/res_config_settings_views.xml
odoo/addons/sale_multicompany_reporting_currency/views/sale_order_views.xml
odoo_addon_sale_multicompany_reporting_currency-15.0.1.0.2.3.dist-info/METADATA
odoo_addon_sale_multicompany_reporting_currency-15.0.1.0.2.3.dist-info/WHEEL
odoo_addon_sale_multicompany_reporting_currency-15.0.1.0.2.3.dist-info/top_level.txt
odoo_addon_sale_multicompany_reporting_currency-15.0.1.0.2.3.dist-info/RECORD
