Metadata-Version: 2.1
Name: odoo-addon-sale-multicompany-reporting-currency
Version: 15.0.1.0.2.3
Summary: Adds Amount in multicompany reporting currency to Sale Order
Home-page: https://github.com/OCA/sale-reporting
Author: Camptocamp SA, Odoo Community Association (OCA)
Author-email: support@odoo-community.org
License: AGPL-3
Platform: UNKNOWN
Classifier: Programming Language :: Python
Classifier: Framework :: Odoo
Classifier: Framework :: Odoo :: 15.0
Classifier: License :: OSI Approved :: GNU Affero General Public License v3
Requires-Python: >=3.8
Requires-Dist: odoo-addon-base-multicompany-reporting-currency <15.1dev,>=15.0dev
Requires-Dist: odoo <15.1dev,>=15.0a
